comiclib/__init__.py
comiclib/__main__.py
comiclib/config.py
comiclib/database.py
comiclib/frontend_boost.py
comiclib/main.py
comiclib/scan.py
comiclib/utils.py
comiclib/LANraragi/COPYING
comiclib/LANraragi/public/robots.txt
comiclib/LANraragi/public/css/config.css
comiclib/LANraragi/public/css/lrr.css
comiclib/LANraragi/public/img/empty.png
comiclib/LANraragi/public/img/flubbed.gif
comiclib/LANraragi/public/img/logo.png
comiclib/LANraragi/public/img/noThumb.png
comiclib/LANraragi/public/img/notfound.jpg
comiclib/LANraragi/public/img/wait_warmly.jpg
comiclib/LANraragi/public/img/theme_preview/hachikuji.png
comiclib/LANraragi/public/img/theme_preview/hverse.png
comiclib/LANraragi/public/img/theme_preview/nadeko.png
comiclib/LANraragi/public/img/theme_preview/sadpanda.png
comiclib/LANraragi/public/img/theme_preview/yotsugi.png
comiclib/LANraragi/public/js/backup.js
comiclib/LANraragi/public/js/batch.js
comiclib/LANraragi/public/js/category.js
comiclib/LANraragi/public/js/common.js
comiclib/LANraragi/public/js/config.js
comiclib/LANraragi/public/js/edit.js
comiclib/LANraragi/public/js/index.js
comiclib/LANraragi/public/js/index_datatables.js
comiclib/LANraragi/public/js/jxl.js
comiclib/LANraragi/public/js/jxl_decoder.min.js
comiclib/LANraragi/public/js/jxl_decoder.wasm
comiclib/LANraragi/public/js/jxl_decoder.worker.js
comiclib/LANraragi/public/js/jxl_decoder_simd.min.js
comiclib/LANraragi/public/js/jxl_decoder_simd.wasm
comiclib/LANraragi/public/js/logs.js
comiclib/LANraragi/public/js/plugins.js
comiclib/LANraragi/public/js/reader.js
comiclib/LANraragi/public/js/server.js
comiclib/LANraragi/public/js/stats.js
comiclib/LANraragi/public/js/translation.js
comiclib/LANraragi/public/js/upload.js
comiclib/LANraragi/public/themes/ex.css
comiclib/LANraragi/public/themes/g.css
comiclib/LANraragi/public/themes/modern.css
comiclib/LANraragi/public/themes/modern_clear.css
comiclib/LANraragi/public/themes/modern_red.css
comiclib/LANraragi/templates/backup
comiclib-0.0.8.dist-info/licenses/LICENSE
comiclib-0.0.8.dist-info/METADATA
comiclib-0.0.8.dist-info/WHEEL
comiclib-0.0.8.dist-info/entry_points.txt
comiclib-0.0.8.dist-info/top_level.txt
comiclib-0.0.8.dist-info/RECORD
