Metadata-Version: 2.4
Name: comiclib
Version: 0.0.8
Summary: Manage, read and share your comic/manga library
Author: URenko
Project-URL: Homepage, https://github.com/comiclib/comiclib
Project-URL: Bug Tracker, https://github.com/comiclib/comiclib/issues
Classifier: Programming Language :: Python :: 3
Classifier: License :: OSI Approved :: MIT License
Classifier: Operating System :: OS Independent
Requires-Python: >=3.9
License-File: LICENSE
Requires-Dist: fastapi
Requires-Dist: pydantic-settings>=2
Requires-Dist: sqlalchemy
Requires-Dist: python-multipart
Requires-Dist: pillow
Requires-Dist: Template-Toolkit-Python
Requires-Dist: watchfiles
Requires-Dist: requests
Provides-Extra: full
Requires-Dist: uvicorn[standard]; extra == "full"
Requires-Dist: psutil; extra == "full"
Requires-Dist: charset_normalizer; extra == "full"
Dynamic: license-file
